GhRobot/Bot.py
GhRobot/Follow.py
GhRobot/Search.py
GhRobot/ToCsv.py
GhRobot/User.py
GhRobot/__init__.py
ShortCode/Code.py
ShortCode/Tool.py
ShortCode/__init__.py
Gh_Robots-0.0.5.dist-info/LICENSE
Gh_Robots-0.0.5.dist-info/METADATA
Gh_Robots-0.0.5.dist-info/WHEEL
Gh_Robots-0.0.5.dist-info/top_level.txt
Gh_Robots-0.0.5.dist-info/RECORD
