Metadata-Version: 2.1
Name: Gh-Robots
Version: 0.0.5
Summary: A Github API-based Robot
Home-page: https://github.com/CoolPlayLin/Gh-Robot
Download-URL: https://github.com/CoolPlayLin/Gh-Robot/releases
Author: CoolPlayLin
Author-email: help@api-coolplaylin.eu.org
License: GPL
Project-URL: Bug Report, https://github.com/CoolPlayLin/Gh-Robot/issues/new?assignees=&labels=bug&template=bug_report.md&title=%5BBug%5D%3A
Project-URL: Feature Request, https://github.com/CoolPlayLin/Gh-Robot/issues/new?assignees=&labels=enhancement&template=feature-request.md&title=%5BFeature+Request%5D
Classifier: Programming Language :: Python :: 3
Classifier: License :: OSI Approved :: GNU General Public License v3 (GPLv3)
License-File: LICENSE
Requires-Dist: requests (>=2.28.1)
Requires-Dist: wget (>=3.2)
Requires-Dist: pandas (>=1.5.0)
